MANIFEST.in
sc-releaser.cfg
setup.cfg
setup.py
Products/__init__.py
Products.CMFContentPanels.egg-info/PKG-INFO
Products.CMFContentPanels.egg-info/SOURCES.txt
Products.CMFContentPanels.egg-info/dependency_links.txt
Products.CMFContentPanels.egg-info/entry_points.txt
Products.CMFContentPanels.egg-info/namespace_packages.txt
Products.CMFContentPanels.egg-info/not-zip-safe
Products.CMFContentPanels.egg-info/requires.txt
Products.CMFContentPanels.egg-info/top_level.txt
Products/CMFContentPanels/CREDIT.txt
Products/CMFContentPanels/ContentPanels.py
Products/CMFContentPanels/ContentPanelsTool.py
Products/CMFContentPanels/FAQ.txt
Products/CMFContentPanels/HISTORY.txt
Products/CMFContentPanels/INSTALL.txt
Products/CMFContentPanels/LICENSE.txt
Products/CMFContentPanels/README.txt
Products/CMFContentPanels/SUPPORT_WIKI.txt
Products/CMFContentPanels/TODO.txt
Products/CMFContentPanels/__init__.py
Products/CMFContentPanels/config.py
Products/CMFContentPanels/configure.zcml
Products/CMFContentPanels/interfaces.py
Products/CMFContentPanels/profiles.zcml
Products/CMFContentPanels/refresh.txt
Products/CMFContentPanels/skins.zcml
Products/CMFContentPanels/tool.gif
Products/CMFContentPanels/version.txt
Products/CMFContentPanels/Extensions/Install.py
Products/CMFContentPanels/browser/__init__.py
Products/CMFContentPanels/browser/subnavtree.py
Products/CMFContentPanels/i18n/contentpanels-plone-cs.po
Products/CMFContentPanels/i18n/contentpanels-plone-de.po
Products/CMFContentPanels/i18n/contentpanels-plone-es.po
Products/CMFContentPanels/i18n/contentpanels-plone-fr.po
Products/CMFContentPanels/i18n/contentpanels-plone-it.po
Products/CMFContentPanels/i18n/contentpanels-plone-pt-br.po
Products/CMFContentPanels/i18n/contentpanels-plone-zh.po
Products/CMFContentPanels/i18n/contentpanels-plone.pot
Products/CMFContentPanels/locales/contentpanels.pot
Products/CMFContentPanels/locales/manual.pot
Products/CMFContentPanels/locales/rebuildAll.sh
Products/CMFContentPanels/locales/cs/LC_MESSAGES/contentpanels.po
Products/CMFContentPanels/locales/de/LC_MESSAGES/contentpanels.po
Products/CMFContentPanels/locales/es/LC_MESSAGES/contentpanels.po
Products/CMFContentPanels/locales/fr/LC_MESSAGES/contentpanels.po
Products/CMFContentPanels/locales/it/LC_MESSAGES/contentpanels.po
Products/CMFContentPanels/locales/nl/LC_MESSAGES/contentpanels.po
