Metadata-Version: 1.0
Name: Products.CMFContentPanels
Version: 2.6a8dev
Summary: CMFContentPanels is a plone portlets product to build composite pages
Home-page: http://svn.plone.org/svn/collective/Products.CMFContentPanels/
Author: Erico Andrei
Author-email: erico@simplesconsultoria.com.br
License: GPL
Keywords: plone web composite_pages CMFContentPanels
Platform: UNKNOWN
Classifier: Programming Language :: Python
Classifier: Framework :: Plone
